cloud_billing_automation/__init__.py
cloud_billing_automation/cba.bat
cloud_billing_automation/helpers.py
cloud_billing_automation/security.py
cloud_billing_automation/validation.py
cloud_billing_automation/alerts/__init__.py
cloud_billing_automation/alerts/anomaly.py
cloud_billing_automation/alerts/base.py
cloud_billing_automation/alerts/budget.py
cloud_billing_automation/alerts/channels.py
cloud_billing_automation/alerts/templates.py
cloud_billing_automation/analyzers/__init__.py
cloud_billing_automation/analyzers/anomaly.py
cloud_billing_automation/analyzers/cost.py
cloud_billing_automation/analyzers/forecast.py
cloud_billing_automation/analyzers/ml_forecaster.py
cloud_billing_automation/analyzers/optimizer.py
cloud_billing_automation/analyzers/trend.py
cloud_billing_automation/cli/__init__.py
cloud_billing_automation/cli/main.py
cloud_billing_automation/cli/commands/__init__.py
cloud_billing_automation/cli/commands/alerts.py
cloud_billing_automation/cli/commands/analyze.py
cloud_billing_automation/cli/commands/budget.py
cloud_billing_automation/cli/commands/config.py
cloud_billing_automation/cli/commands/credentials.py
cloud_billing_automation/cli/commands/optimize.py
cloud_billing_automation/collectors/__init__.py
cloud_billing_automation/collectors/aws_collector.py
cloud_billing_automation/collectors/azure_collector.py
cloud_billing_automation/collectors/base.py
cloud_billing_automation/collectors/gcp_collector.py
cloud_billing_automation/core/__init__.py
cloud_billing_automation/core/config.py
cloud_billing_automation/core/credentials.py
cloud_billing_automation/core/exceptions.py
cloud_billing_automation/core/logging_config.py
cloud_billing_automation/reports/__init__.py
cloud_billing_automation/reports/scheduler.py
cloud_billing_automation-0.5.2.dist-info/licenses/LICENSE
cloud_billing_automation-0.5.2.dist-info/METADATA
cloud_billing_automation-0.5.2.dist-info/WHEEL
cloud_billing_automation-0.5.2.dist-info/entry_points.txt
cloud_billing_automation-0.5.2.dist-info/top_level.txt
cloud_billing_automation-0.5.2.dist-info/RECORD
