Metadata-Version: 2.4
Name: cloud-billing-automation
Version: 0.5.2
Summary: DevOps-centric cloud cost governance and automation tool
Author-email: H A R S H H A A <contact@example.com>
License: MIT License
Project-URL: Homepage, https://github.com/NotHarshhaa/cloud-billing-automation
Project-URL: Repository, https://github.com/NotHarshhaa/cloud-billing-automation
Project-URL: Documentation, https://github.com/NotHarshhaa/cloud-billing-automation/docs
Project-URL: Bug Tracker, https://github.com/NotHarshhaa/cloud-billing-automation/issues
Keywords: cloud,billing,devops,cost,automation,finops
Classifier: Development Status :: 3 - Alpha
Classifier: Intended Audience :: Developers
Classifier: Intended Audience :: System Administrators
Classifier: License :: OSI Approved :: MIT License
Classifier: Operating System :: OS Independent
Classifier: Programming Language :: Python :: 3
Classifier: Programming Language :: Python :: 3.8
Classifier: Programming Language :: Python :: 3.9
Classifier: Programming Language :: Python :: 3.10
Classifier: Programming Language :: Python :: 3.11
Classifier: Topic :: System :: Systems Administration
Classifier: Topic :: Office/Business :: Financial
Requires-Python: >=3.8
License-File: LICENSE
Requires-Dist: click>=8.1.0
Requires-Dist: pyyaml>=6.0
Requires-Dist: requests>=2.28.0
Requires-Dist: python-dateutil>=2.8.2
Requires-Dist: boto3>=1.26.0
Requires-Dist: google-cloud-billing>=1.10.0
Requires-Dist: azure-mgmt-billing>=4.0.0
Requires-Dist: azure-identity>=1.12.0
Requires-Dist: pandas>=1.5.0
Requires-Dist: numpy>=1.24.0
Requires-Dist: cryptography>=3.4.8
Requires-Dist: keyring>=23.13.0
Requires-Dist: jinja2>=3.1.0
Requires-Dist: matplotlib>=3.6.0
Requires-Dist: seaborn>=0.12.0
Requires-Dist: rich>=13.0.0
Requires-Dist: typer>=0.7.0
Requires-Dist: structlog>=22.3.0
Requires-Dist: schedule>=1.2.0
Provides-Extra: dev
Requires-Dist: pytest>=7.2.0; extra == "dev"
Requires-Dist: pytest-cov>=4.0.0; extra == "dev"
Requires-Dist: black>=22.10.0; extra == "dev"
Requires-Dist: flake8>=5.0.0; extra == "dev"
Requires-Dist: mypy>=0.991; extra == "dev"
Dynamic: license-file
